cloud/__init__.py
oscillink/__init__.py
oscillink/py.typed
oscillink/adapters/text.py
oscillink/core/graph.py
oscillink/core/lattice.py
oscillink/core/perf.py
oscillink/core/provenance.py
oscillink/core/receipts.py
oscillink/core/solver.py
oscillink_lattice-0.1.5.dist-info/licenses/LICENSE
oscillink_lattice-0.1.5.dist-info/METADATA
oscillink_lattice-0.1.5.dist-info/WHEEL
oscillink_lattice-0.1.5.dist-info/top_level.txt
oscillink_lattice-0.1.5.dist-info/RECORD
