Metadata-Version: 2.4
Name: oscillink-lattice
Version: 0.1.5
Summary: Oscillink Lattice — Short-Term Coherence SDK (physics-inspired memory for generative models)
Author-email: Oscillink <contact@oscillink.com>
License: Apache-2.0
Keywords: graph,lattice,memory,retrieval,ai,ml,coherence,physics-inspired
Classifier: Development Status :: 3 - Alpha
Classifier: Intended Audience :: Developers
Classifier: Intended Audience :: Science/Research
Classifier: Topic :: Scientific/Engineering :: Artificial Intelligence
Classifier: Topic :: Scientific/Engineering :: Information Analysis
Classifier: License :: OSI Approved :: Apache Software License
Classifier: Programming Language :: Python
Classifier: Programming Language :: Python :: 3
Classifier: Programming Language :: Python :: 3.9
Classifier: Programming Language :: Python :: 3.10
Classifier: Programming Language :: Python :: 3.11
Classifier: Programming Language :: Python :: 3.12
Requires-Python: >=3.9
License-File: LICENSE
Requires-Dist: numpy<2.0,>=1.22
Requires-Dist: typing_extensions>=4.7
Provides-Extra: dev
Requires-Dist: pytest>=7.0; extra == "dev"
Requires-Dist: pytest-cov>=4.1; extra == "dev"
Requires-Dist: ruff>=0.5.0; extra == "dev"
Requires-Dist: mypy>=1.5; extra == "dev"
Requires-Dist: pre-commit>=3.7; extra == "dev"
Requires-Dist: fastapi>=0.111; extra == "dev"
Requires-Dist: httpx>=0.27; extra == "dev"
Provides-Extra: cloud
Requires-Dist: fastapi>=0.111; extra == "cloud"
Requires-Dist: uvicorn[standard]>=0.30; extra == "cloud"
Requires-Dist: pydantic>=2.5; extra == "cloud"
Requires-Dist: orjson>=3.9; extra == "cloud"
Requires-Dist: python-multipart>=0.0.6; extra == "cloud"
Requires-Dist: prometheus-client>=0.20; extra == "cloud"
Provides-Extra: billing
Requires-Dist: stripe>=10.0; extra == "billing"
Requires-Dist: google-cloud-firestore>=2.16; extra == "billing"
Provides-Extra: cloud-all
Requires-Dist: fastapi>=0.111; extra == "cloud-all"
Requires-Dist: uvicorn[standard]>=0.30; extra == "cloud-all"
Requires-Dist: pydantic>=2.5; extra == "cloud-all"
Requires-Dist: orjson>=3.9; extra == "cloud-all"
Requires-Dist: python-multipart>=0.0.6; extra == "cloud-all"
Requires-Dist: prometheus-client>=0.20; extra == "cloud-all"
Requires-Dist: stripe>=10.0; extra == "cloud-all"
Requires-Dist: google-cloud-firestore>=2.16; extra == "cloud-all"
Dynamic: license-file
